{
    "players": [
      {
        "name": "Lionel Messi",
        "photo": "https://cdn.sofifa.net/players/158/023/25_120.png",
        "position": "RW",
        "nationality": "Argentina",
        "flag": "https://cdn.sofifa.net/flags/ar.png",
        "club": "Inter Miami",
        "logo": "https://cdn.sofifa.net/meta/team/239235/120.png",
        "rating": 93,
        "pace": 85,
        "shooting": 92,
        "passing": 91,
        "dribbling": 95,
        "defending": 35,
        "physical": 65
      },
      {
        "name": "Cristiano Ronaldo",
        "photo": "https://cdn.sofifa.net/players/020/801/25_120.png",
        "position": "ST",
        "nationality": "Portugal",
        "flag": "https://cdn.sofifa.net/flags/pt.png",
        "club": "Al Nassr",
        "logo": "https://cdn.sofifa.net/meta/team/2506/120.png",
        "rating": 91,
        "pace": 84,
        "shooting": 94,
        "passing": 82,
        "dribbling": 87,
        "defending": 34,
        "physical": 77
      },
      {
        "name": "Kevin De Bruyne",
        "photo": "https://cdn.sofifa.net/players/192/985/25_120.png",
        "position": "CM",
        "nationality": "Belgium",
        "flag": "https://cdn.sofifa.net/flags/be.png",
        "club": "Manchester City",
        "logo": "https://cdn.sofifa.net/players/239/085/25_120.png",
        "rating": 91,
        "pace": 74,
        "shooting": 86,
        "passing": 93,
        "dribbling": 88,
        "defending": 64,
        "physical": 78
      },
      {
        "name": "Kylian Mbappé",
        "photo": "https://cdn.sofifa.net/players/231/747/25_120.png",
        "position": "ST",
        "nationality": "France",
        "flag": "https://cdn.sofifa.net/flags/fr.png",
        "club": "Real Madrid",
        "logo": "https://cdn.sofifa.net/meta/team/3468/120.png",
        "rating": 92,
        "pace": 97,
        "shooting": 89,
        "passing": 80,
        "dribbling": 92,
        "defending": 39,
        "physical": 77
      }

    ]
  }
  